AIStructDynSolve/__init__.py
AIStructDynSolve/config.py
AIStructDynSolve/LossFunctions/Gradients.py
AIStructDynSolve/LossFunctions/LossEQ.py
AIStructDynSolve/LossFunctions/LossEQ2D.py
AIStructDynSolve/LossFunctions/LossEQ3D.py
AIStructDynSolve/LossFunctions/LossPt.py
AIStructDynSolve/LossFunctions/LossPtFunc.py
AIStructDynSolve/LossFunctions/__init__.py
AIStructDynSolve/NeuralNetwork/FKAN.py
AIStructDynSolve/NeuralNetwork/FNN.py
AIStructDynSolve/NeuralNetwork/HardBC.py
AIStructDynSolve/NeuralNetwork/KAN.py
AIStructDynSolve/NeuralNetwork/MaFNN.py
AIStructDynSolve/NeuralNetwork/MaPFNN.py
AIStructDynSolve/NeuralNetwork/MsFFN.py
AIStructDynSolve/NeuralNetwork/MsPFFN.py
AIStructDynSolve/NeuralNetwork/NN.py
AIStructDynSolve/NeuralNetwork/PFNN.py
AIStructDynSolve/NeuralNetwork/RBFKAN.py
AIStructDynSolve/NeuralNetwork/__init__.py
AIStructDynSolve/Newmark/NewmarkIntegrator_EQ.py
AIStructDynSolve/Newmark/NewmarkIntegrator_EQ2D.py
AIStructDynSolve/Newmark/NewmarkIntegrator_EQ3D.py
AIStructDynSolve/Newmark/NewmarkIntegrator_Pt.py
AIStructDynSolve/Newmark/NewmarkIntegrator_PtFunc.py
AIStructDynSolve/Newmark/__init__.py
AIStructDynSolve/Postprocessor/Predictor.py
AIStructDynSolve/Postprocessor/Visualizer.py
AIStructDynSolve/Postprocessor/Visualizer_Newmark.py
AIStructDynSolve/Postprocessor/Visualizer_SVM.py
AIStructDynSolve/Postprocessor/__init__.py
AIStructDynSolve/SVM/RBFKernel.py
AIStructDynSolve/SVM/SVM_EQ.py
AIStructDynSolve/SVM/SVM_Pt.py
AIStructDynSolve/SVM/SVM_PtFunc.py
AIStructDynSolve/SVM/__init__.py
AIStructDynSolve/StructDynSystem/ModalAnalyzer.py
AIStructDynSolve/StructDynSystem/StructDynSystemParm.py
AIStructDynSolve/StructDynSystem/__init__.py
AIStructDynSolve/StructDynSystem/inputEQ.py
AIStructDynSolve/StructDynSystem/inputEQ2D.py
AIStructDynSolve/StructDynSystem/inputEQ3D.py
AIStructDynSolve/StructDynSystem/inputPt.py
AIStructDynSolve/StructDynSystem/inputPtFunc.py
AIStructDynSolve/Trainer/TrainerForwardProblem.py
AIStructDynSolve-1.14.dist-info/LICENSE
AIStructDynSolve-1.14.dist-info/METADATA
AIStructDynSolve-1.14.dist-info/WHEEL
AIStructDynSolve-1.14.dist-info/top_level.txt
AIStructDynSolve-1.14.dist-info/RECORD
