Metadata-Version: 2.1
Name: AIStructDynSolve
Version: 1.14
Summary: AI-powered framework to solve both forward and inverse problems in structural dynamics
Home-page: https://github.com/duke-iem/AIStructDynSolve.git
Author: Ke Du(杜轲)
Author-email: duke@iem.ac.cn
Classifier: Programming Language :: Python :: 3
Classifier: Operating System :: OS Independent
Requires-Python: >=3.10
License-File: LICENSE
Requires-Dist: matplotlib
Requires-Dist: numpy
Requires-Dist: scikit-optimize
Requires-Dist: scipy
Requires-Dist: pandas
Requires-Dist: openpyxl
